ultrastar_pitch/__init__.py
ultrastar_pitch/__main__.py
ultrastar_pitch/audio_preprocessor.py
ultrastar_pitch/detection_pipeline.py
ultrastar_pitch/gui.py
ultrastar_pitch/pitch_classifier.py
ultrastar_pitch/pitch_utils.py
ultrastar_pitch/project_parser.py
ultrastar_pitch/stochastic_postprocessor.py
ultrastar_pitch/ultrastar_pitch.py
ultrastar_pitch/version.py
ultrastar_pitch/binaries/icon.ico
ultrastar_pitch/binaries/icon.png
ultrastar_pitch/binaries/pitchnet_2020_12_14.onnx
ultrastar_pitch-1.0.1.dist-info/LICENSE
ultrastar_pitch-1.0.1.dist-info/METADATA
ultrastar_pitch-1.0.1.dist-info/WHEEL
ultrastar_pitch-1.0.1.dist-info/entry_points.txt
ultrastar_pitch-1.0.1.dist-info/top_level.txt
ultrastar_pitch-1.0.1.dist-info/RECORD
