Metadata-Version: 2.1
Name: ultrastar-pitch
Version: 1.0.1
Summary: Automate the pitch detection process for Ultrastar Deluxe karaoke projects
Home-page: https://github.com/paradigmn/ultrastar_pitch
Author: paradigm
Author-email: ultrastarpitch@gmail.com
License: UNKNOWN
Platform: UNKNOWN
Classifier: Intended Audience :: End Users/Desktop
Classifier: Operating System :: Microsoft :: Windows
Classifier: Operating System :: POSIX :: Linux
Classifier: Development Status :: 5 - Production/Stable
Classifier: License :: OSI Approved :: MIT License
Classifier: Programming Language :: Python
Classifier: Programming Language :: Python :: 3 :: Only
Classifier: Programming Language :: Python :: 3.7
Classifier: Programming Language :: Python :: 3.8
Classifier: Topic :: Multimedia :: Sound/Audio :: Analysis
Classifier: Topic :: Scientific/Engineering :: Information Analysis
Classifier: Topic :: Scientific/Engineering :: Mathematics
Classifier: Topic :: Scientific/Engineering :: Artificial Intelligence
Classifier: Intended Audience :: End Users/Desktop
Requires-Dist: onnxruntime
Requires-Dist: scipy
Requires-Dist: numpy
